<?xml version="1.0" encoding="utf-8"?>
<form
	cssfiles="media://com_akeebasubs/css/backend.css"
	type="browse"
	show_header="1"
	show_filters="1"
	show_pagination="1"
	norows_placeholder="COM_AKEEBASUBS_COMMON_NORECORDS"
>
	<headerset>
		<header name="akeebasubs_subscription_id" type="Searchable"
				filterclass="input-small"
				tdwidth="100" sortable="true" />

		<header name="akeebasubs_invoice_id" type="RowSelect"
				tdwidth="20px"
		/>
		
		<header name="user_id" type="Searchable"
				label="COM_AKEEBASUBS_SUBSCRIPTIONS_USER"
				filterclass="input-small"
				searchfieldname="user"
				sortable="true" tdwidth="15%"
		/>
		
		<header name="extension" type="Selectable"
				sortable="true" tdwidth="10%"
				source_class="Akeeba\Subscriptions\Admin\Helper\Select"
                source_method="getInvoiceExtensions"
		/>
		
		<header name="invoice_no" type="Searchable"
				filterclass="input-small"
				sortable="true" tdwitdh="10%" />
		
		<header name="invoice_date" type="Date"
				filterclass="input-small"
				sortable="true" tdwitdh="10%" />
		
		<header name="actions" type="Field"
				label="COM_AKEEBASUBS_INVOICES_LBL_ACTIONS"
				sortable="false" />
	</headerset>

	<fieldset name="items">
		<field name="akeebasubs_subscription_id" type="Text" format="%05d" />
		
		<field name="akeebasubs_invoice_id" type="SelectRow" />
		
		<field name="user_id" type="User"
			avatar_size="48"
			show_link="false"
			link_url="index.php?option=com_akeebasubs&amp;view=User&amp;id=[USER:ID]"
		/>
		
		<field name="extension" type="GenericList"
				sortable="true" tdwidth="10%"
                source_class="Akeeba\Subscriptions\Admin\Helper\Select"
                source_method="getInvoiceExtensions"
		/>

		<field name="invoice_no" type="InvoiceNumber"/>
		
		<field name="invoice_date" type="Calendar"/>
		
		<field name="actions" type="InvoiceActions"/>
	</fieldset>
</form>